{
  "title": "Non-frontal face recognition using GANs and memristor-based classifiers",
  "link": "https://arxiv.org/abs/2606.12074v1",
  "published": "2026-06-10T13:41:00Z",
  "updated": "2026-06-10T13:41:00Z",
  "summary": "Face recognition systems have advanced significantly through deep learning techniques, delivering high performance and robustness in complex scenarios. However, these approaches incur substantial computational overhead, limiting their in situ applicability in resource-constrained platforms such as drones, where they can address challenges including non-frontal facial imagery. Memristor-based neuromorphic systems have emerged as a compelling approach for edge AI applications, combining biologically inspired processing with efficient and scalable computation. In this work, we propose a facial recognition framework that addresses non-frontal pose variations by integrating lightweight generative adversarial network (GAN)-based pose frontalisation with memristor-based neuromorphic recognition. The experimental results on two datasets demonstrate the effectiveness of combining adversarial learning with memristive technology, achieving up to 96% identification accuracy. The proposed approach alleviates the computational bottlenecks of conventional AI and offers a scalable, efficient solution for face recognition in dynamic real-world environments.",
  "id": "http://arxiv.org/abs/2606.12074v1",
  "authors": [
    "Semih Vazgecen",
    "Cristian Sestito",
    "Spyros Stathopoulos",
    "Themis Prodromakis"
  ],
  "categories": [
    "cs.CV",
    "cs.AI",
    "eess.IV"
  ],
  "pdf_link": "https://arxiv.org/pdf/2606.12074v1"
}