{
  "title": "The Integrator Advantage: Controlled Agentic AI for Small and Medium-Sized Companies",
  "link": "https://arxiv.org/abs/2606.16649v1",
  "published": "2026-06-15T12:38:53Z",
  "updated": "2026-06-15T12:38:53Z",
  "summary": "Agentic AI marks a new phase of enterprise automation. Unlike traditional automation or conversational AI, agentic systems can interpret goals, plan multi step tasks, access tools, interact with enterprise systems, and execute workflows with varying degrees of autonomy. For small and medium sized companies, this creates potential to reduce administrative burden, accelerate routine processes, and improve the use of organizational knowledge. This paper argues that the near term value of Agentic AI does not lie in full autonomy or workforce reduction, but in controlled partial autonomy for simple and medium complexity business processes. It proposes an integration framework covering use case suitability, autonomy levels, technical integration, governance, security, employee enablement, and measurable impact. The paper concludes that Agentic AI can become a productivity lever when implemented as a human centered capability with responsibility and accountability retained by people.",
  "id": "http://arxiv.org/abs/2606.16649v1",
  "authors": [
    "Christopner Koch",
    "Joshua A. Wellbrock"
  ],
  "categories": [
    "cs.AI"
  ],
  "pdf_link": "https://arxiv.org/pdf/2606.16649v1"
}