{
  "title": "Memorizing chemical element symbols",
  "link": "https://www.johndcook.com/blog/2026/01/07/chemical-element-symbols/",
  "published": "Wed, 07 Jan 2026 13:58:01 +0000",
  "summary": "<p>Here&#8217;s something I&#8217;ve wondered about before: are there good mnemonics for chemical element symbols? Some element symbols are based on Latin or German names and seem arbitrary to English speakers, such as K (kalium) for potassium or Fe (ferrum) for iron. However, these elements are very common and so their names and symbols are familiar. [&#8230;]</p>\nThe post <a href=\"https://www.johndcook.com/blog/2026/01/07/chemical-element-symbols/\">Memorizing chemical element symbols</a> first appeared on <a href=\"https://www.johndcook.com/blog\">John D. Cook</a>.",
  "id": "https://www.johndcook.com/blog/?p=246779"
}