{
  "title": "Corona-Update november: Twee vaccins en sneltests!",
  "link": "https://berthub.eu/articles/posts/corona-update-november/",
  "published": "Mon, 16 Nov 2020 12:42:49 +0100",
  "summary": "Ja, daar zijn we weer! Voor het eerst [sinds juli](https://berthub.eu/articles/posts/corona-update-eind-juli/) weer een Corona Update. Er is inmiddels weer genoeg te melden: vaccins, tests, cijfers, medicijnen en vitamine D. Vaccins Om te beginnen, wow. En nog een keer wow. SINDS VANDAAG ER ZIJN TWEE WERKENDE VACCINS! En nog gekker, ze zijn in februari 2020 al ontworpen, toen het RNA (de broncode) van het virus pas net bekend was. Vergeleken met zelfs maar een paar jaar geleden is dit pure science fiction.",
  "id": "https://berthub.eu/articles/posts/corona-update-november/"
}