{
  "title": "History of PowerDNS: 2003-2013",
  "link": "https://berthub.eu/articles/posts/history-of-powerdns-2003-2013/",
  "published": "Sun, 29 Nov 2020 16:24:11 +0100",
  "summary": "This is part two of the PowerDNS history as I recall it. As noted in part one, some of this stuff is rather old, and it is entirely possible I am misremembering things. Please do let me know if you find any important omissions or mistakes!\nAt the end of 2002, beginning of 2003, PowerDNS as a going concern was gone. There were no more employees, there were no paying customers.",
  "id": "https://berthub.eu/articles/posts/history-of-powerdns-2003-2013/"
}